alauda-0.3.8.dist-info/WHEEL
alauda-0.3.8.dist-info/METADATA
alauda-0.3.8.dist-info/DESCRIPTION.rst
alauda-0.3.8.dist-info/entry_points.txt
alauda-0.3.8.dist-info/top_level.txt
alauda-0.3.8.dist-info/RECORD
alauda-0.3.8.dist-info/metadata.json
clitests/__init__.py
clitests/parser_tests.py
clitests/e2e_tests.py
alaudacli/service.py
alaudacli/exceptions.py
alaudacli/application.py
alaudacli/instance.py
alaudacli/__init__.py
alaudacli/alauda_cli.py
alaudacli/build.py
alaudacli/project.py
alaudacli/compose.py
alaudacli/cmd_parser.py
alaudacli/backup.py
alaudacli/organization.py
alaudacli/auth.py
alaudacli/commands.py
alaudacli/cmd_processor.py
alaudacli/execute.py
alaudacli/settings.py
alaudacli/interactive.py
alaudacli/util.py
