Metadata-Version: 2.0
Name: alauda
Version: 0.3.8
Summary: Alauda CLI
Home-page: https://www.alauda.io
Author: alauda.io
Author-email: info@mathildetech.com
License: UNKNOWN
Keywords: alauda
Platform: UNKNOWN
Classifier: Development Status :: 3 - Alpha
Classifier: Intended Audience :: Developers
Classifier: Topic :: Software Development :: Build Tools
Classifier: Programming Language :: Python :: 2
Classifier: Programming Language :: Python :: 2.6
Classifier: Programming Language :: Python :: 2.7
Classifier: Programming Language :: Python :: 3
Classifier: Programming Language :: Python :: 3.2
Classifier: Programming Language :: Python :: 3.3
Classifier: Programming Language :: Python :: 3.4
Requires-Dist: mock (>=1.0.1)
Requires-Dist: PyYAML (>=3.10)
Requires-Dist: pyOpenSSL (>=0.14)
Requires-Dist: requests (>=2.4.3)
Requires-Dist: requests-oauthlib (>=0.4.2)
Requires-Dist: paramiko (>=1.15.2)
